{
  "motion_id": "sit_up",
  "motion_name": "仰卧起坐",
  "version": "2.2.0",
  "description": "严格对照《国家学生体质健康标准》的仰卧起坐规则（扩展变量版）",
  "landmarks_required": [
    "left_shoulder",
    "right_shoulder",
    "left_hip",
    "right_hip",
    "left_knee",
    "right_knee",
    "left_ankle",
    "right_ankle",
    "nose"
  ],
  "enabled_metrics": [
    "left_knee",
    "right_knee",
    "trunk_ground_angle",
    "knee_angle_variation",
    "rep_cycle_duration",
    "neck_flexion_angle",
    "lumbar_gap_distance"
  ],
  "metric_rules": {
    "left_knee": {
      "normal_range": {
        "min": 85.0,
        "max": 95.0
      },
      "severity_rules": {
        "mild": [80.0, 85.0],
        "moderate": [70.0, 80.0],
        "severe": [0.0, 70.0]
      }
    },
    "right_knee": {
      "normal_range": {
        "min": 85.0,
        "max": 95.0
      },
      "severity_rules": {
        "mild": [95.0, 100.0],
        "moderate": [100.0, 110.0],
        "severe": [110.0, 180.0]
      }
    },
    "trunk_ground_angle": {
      "normal_range": {
        "min": 30.0,
        "max": 45.0
      },
      "severity_rules": {
        "mild": [20.0, 30.0],
        "moderate": [10.0, 20.0],
        "severe": [0.0, 10.0]
      }
    },
    "knee_angle_variation": {
      "normal_range": {
        "min": 0.0,
        "max": 15.0
      },
      "severity_rules": {
        "mild": [15.0, 20.0],
        "moderate": [20.0, 30.0],
        "severe": [30.0, 180.0]
      }
    },
    "rep_cycle_duration": {
      "normal_range": {
        "min": 1.2,
        "max": 3.0
      },
      "severity_rules": {
        "mild": [0.8, 1.2],
        "moderate": [0.5, 0.8],
        "severe": [0.0, 0.5]
      }
    },
    "neck_flexion_angle": {
      "normal_range": {
        "min": 0.0,
        "max": 20.0
      },
      "severity_rules": {
        "mild": [20.0, 25.0],
        "moderate": [25.0, 35.0],
        "severe": [35.0, 180.0]
      }
    },
    "lumbar_gap_distance": {
      "normal_range": {
        "min": 0.0,
        "max": 0.03
      },
      "severity_rules": {
        "mild": [0.03, 0.05],
        "moderate": [0.05, 0.08],
        "severe": [0.08, 1.0]
      }
    }
  },
  "voice_prompts": {
    "left_knee": {
      "mild": "左膝角度略有偏差，请保持屈膝接近九十度",
      "moderate": "左膝角度不规范，请调整腿部支撑姿态",
      "severe": "左膝角度明显异常，请立即调整准备姿势"
    },
    "right_knee": {
      "mild": "右膝角度略有偏差，请保持屈膝接近九十度",
      "moderate": "右膝角度不规范，请调整腿部支撑姿态",
      "severe": "右膝角度明显异常，请立即调整准备姿势"
    },
    "trunk_ground_angle": {
      "mild": "再起高一点，肘部向膝盖靠近",
      "moderate": "动作幅度不足，请继续卷腹",
      "severe": "动作幅度明显不足，请重新发力"
    },
    "knee_angle_variation": {
      "mild": "双腿略有晃动，请保持下肢稳定",
      "moderate": "腿部借力明显，请减少下肢代偿",
      "severe": "双腿借力严重，请立即调整发力方式"
    },
    "rep_cycle_duration": {
      "mild": "动作稍快，请放慢节奏",
      "moderate": "动作过快，请控制起落速度",
      "severe": "速度明显过快，请重新控制动作节奏"
    },
    "neck_flexion_angle": {
      "mild": "颈部略有代偿，请放松颈部",
      "moderate": "不要用手拉头，下巴微收，眼睛看膝盖",
      "severe": "颈部代偿明显，请立即调整发力方式"
    },
    "lumbar_gap_distance": {
      "mild": "腰部略有离地风险，请收紧核心",
      "moderate": "腰部贴紧垫子，不要悬空",
      "severe": "腰部代偿明显，请立即调整动作"
    }
  },
  "timing": {
    "stable_frames": 5,
    "voice_cooldown_ms": 2000,
    "min_hold_ms": 500
  },
  "tags": [
    "core",
    "sit_up",
    "student_fitness",
    "national_standard"
  ],
  "extras": {
    "future_metrics": [
      "quality_score"
    ]
  }
}